tidytwitter/__init__.py
tidytwitter/tidytwitter.py
tidytwitter-0.2.0.dist-info/LICENSE
tidytwitter-0.2.0.dist-info/METADATA
tidytwitter-0.2.0.dist-info/WHEEL
tidytwitter-0.2.0.dist-info/entry_points.txt
tidytwitter-0.2.0.dist-info/top_level.txt
tidytwitter-0.2.0.dist-info/RECORD
