Metadata-Version: 2.1
Name: tidytwitter
Version: 0.2.0
Summary: Delete your old tweets and favorites using the Twitter API
Home-page: https://github.com/mikepqr/tidytwitter
Author: Mike Lee Williams
Author-email: mike@mike.place
License: UNKNOWN
Project-URL: Bug Reports, https://github.com/mikepqr/tidytwitter/issues
Project-URL: Source, https://github.com/mikepqr/tidytwitter
Keywords: twitter
Platform: UNKNOWN
Classifier: Development Status :: 4 - Beta
Classifier: Environment :: Console
Classifier: Intended Audience :: End Users/Desktop
Classifier: Topic :: Utilities
Classifier: License :: OSI Approved :: MIT License
Classifier: Programming Language :: Python :: 3
Classifier: Programming Language :: Python :: 3.7
Classifier: Programming Language :: Python :: 3.8
Classifier: Programming Language :: Python :: 3.9
Classifier: Programming Language :: Python :: 3.10
Classifier: Programming Language :: Python :: 3 :: Only
Requires-Python: >=3.7
License-File: LICENSE
Requires-Dist: tweepy
Requires-Dist: click
